dreamml/__init__.py
dreamml/config/__init__.py
dreamml/config/_base_config.py
dreamml/config/_legacy.py
dreamml/config/_resolvers.py
dreamml/config/config.py
dreamml/config/default.yaml
dreamml/config/data/__init__.py
dreamml/config/data/default.yaml
dreamml/config/models/__init__.py
dreamml/config/models/default.yaml
dreamml/config/pipeline/__init__.py
dreamml/config/pipeline/default.yaml
dreamml/config/pipeline/reproducibility/__init__.py
dreamml/config/pipeline/reproducibility/default.yaml
dreamml/config/pipeline/saving/__init__.py
dreamml/config/pipeline/saving/default.yaml
dreamml/config/stages/__init__.py
dreamml/config/stages/default.yaml
dreamml/config/task_defaults/__init__.py
dreamml/config/task_defaults/amts.yaml
dreamml/config/task_defaults/amts_ad.yaml
dreamml/config/task_defaults/anomaly_detection.yaml
dreamml/config/task_defaults/binary.yaml
dreamml/config/task_defaults/multiclass.yaml
dreamml/config/task_defaults/multilabel.yaml
dreamml/config/task_defaults/multiregression.yaml
dreamml/config/task_defaults/phrase_retrieval.yaml
dreamml/config/task_defaults/regression.yaml
dreamml/config/task_defaults/timeseries.yaml
dreamml/config/task_defaults/topic_modeling.yaml
dreamml/config/validation/__init__.py
dreamml/config/validation/default.yaml
dreamml/configs/__init__.py
dreamml/configs/config_checker.py
dreamml/configs/config_storage.py
dreamml/data/__init__.py
dreamml/data/_amts_dataset.py
dreamml/data/_dataset.py
dreamml/data/_encoder.py
dreamml/data/_enums.py
dreamml/data/_hadoop.py
dreamml/data/_transformer.py
dreamml/data/entities.py
dreamml/data/exceptions.py
dreamml/data/store.py
dreamml/deployment/__init__.py
dreamml/deployment/deployment.py
dreamml/features/__init__.py
dreamml/features/categorical/__init__.py
dreamml/features/categorical/_base.py
dreamml/features/categorical/_label_encoder.py
dreamml/features/categorical/_one_hot_encoder.py
dreamml/features/categorical/_ordinal_encoder.py
dreamml/features/categorical/_utils.py
dreamml-3.6.3.dist-info/LICENSE
dreamml-3.6.3.dist-info/METADATA
dreamml-3.6.3.dist-info/WHEEL
dreamml-3.6.3.dist-info/top_level.txt
dreamml-3.6.3.dist-info/RECORD
