Metadata-Version: 2.1
Name: dreamml
Version: 3.6.3
Summary: Framework for creating, running and validation of ML models on tabular data
Author: 'Nikita Buts, Nikita Varganov, Alexander Izyurov, Ivan Plotnikov, Maidari Tsydenov, Evgeny Tkachenko, Ilya Ivanov'
Requires-Python: >=3.8
License-File: LICENSE
Requires-Dist: torch>=2.0
Requires-Dist: numpy<2.0,>=1.24.0
Requires-Dist: numba>=0.58.1
Requires-Dist: pandas<1.5,>=1.4.3
Requires-Dist: matplotlib>=3.3.4
Requires-Dist: pip>=22.1
Requires-Dist: seaborn>=0.12.1
Requires-Dist: scipy<1.13.0,>=1.6.3
Requires-Dist: scikit-learn<1.2,>=1.0.2
Requires-Dist: ipython>=8.12.0
Requires-Dist: tqdm>=4.63.0
Requires-Dist: pyspark<3.4,>=3.2.1
Requires-Dist: catboost>=1.2.6
Requires-Dist: lightautoml>=0.4.1
Requires-Dist: lightgbm>=3.2.1
Requires-Dist: bayesian-optimization==1.2.0
Requires-Dist: fairlearn==0.6.2
Requires-Dist: hyperopt==0.2.7
Requires-Dist: Jinja2==3.1.2
Requires-Dist: joblib==1.2.0
Requires-Dist: openpyxl==3.0.10
Requires-Dist: optuna<4.1.0,>=4.0.0
Requires-Dist: py4j==0.10.9.5
Requires-Dist: PyYAML==6.0.0
Requires-Dist: shap<0.45,>=0.42.1
Requires-Dist: XlsxWriter==1.4.3
Requires-Dist: xgboost>=2.0.3
Requires-Dist: workalendar==17.0.0
Requires-Dist: etna==2.7.1
Requires-Dist: Bottleneck<=1.4.0
Requires-Dist: prophet==1.1.5
Requires-Dist: statsmodels==0.13.5
Requires-Dist: colorama>=0.4.6
Requires-Dist: py-boost==0.4.3
Requires-Dist: autowoe>=1.3.3
Requires-Dist: ipynbname>=2023.2.0.0
Requires-Dist: pydantic>=2.6
Requires-Dist: requests>=2.0
Requires-Dist: scikit-multilearn==0.2.0
Requires-Dist: nltk==3.9.1
Requires-Dist: gensim==4.1.0
Requires-Dist: pymystem3==0.2.0
Requires-Dist: simhash==2.1.2
Requires-Dist: nlpaug==1.1.11
Requires-Dist: transformers==4.42.4
Requires-Dist: pytorch-lightning==2.2.5
Requires-Dist: evaluate==0.4.2
Requires-Dist: natasha==1.6.0
Requires-Dist: ruslingua==1.0.0
Requires-Dist: PyMultiDictionary==1.2.4
Requires-Dist: fasttext-wheel==0.9.2
Requires-Dist: sacremoses==0.1.1
Requires-Dist: sentencepiece==0.2.0
Requires-Dist: sentence-transformers==3.0.1
Requires-Dist: bertopic==0.16.3
Requires-Dist: kaleido==0.2.1
Requires-Dist: reportlab>=3.6.12
Requires-Dist: hydra-core>=1.3.0
Requires-Dist: omegaconf>=2.3.0
Requires-Dist: scikit-optimize>=0.10.2
Requires-Dist: peft<0.14.0,>=0.13.0
Requires-Dist: bentoml>=1.3.5
Requires-Dist: deepchecks==0.19.1
Requires-Dist: ambrosia==0.4.1
Provides-Extra: tests
Requires-Dist: pytest>=8.2.1; extra == "tests"
Requires-Dist: black>=24.4.2; extra == "tests"
Requires-Dist: notebook<7,>=6.5.7; extra == "tests"
